dogslow_sentry/__init__.py
dogslow_sentry/timer.py
dogslow_sentry-2.0.1.dist-info/COPYING.txt
dogslow_sentry-2.0.1.dist-info/METADATA
dogslow_sentry-2.0.1.dist-info/WHEEL
dogslow_sentry-2.0.1.dist-info/top_level.txt
dogslow_sentry-2.0.1.dist-info/RECORD
