Metadata-Version: 2.1
Name: dogslow-sentry
Version: 2.0.1
Summary: A Django middleware that logs tracebacks of slow requests to Sentry.
Home-page: https://github.com/intgr/dogslow-sentry
Author: Marti Raudsepp
Author-email: marti@juffo.org
License: GNU LGPL
Project-URL: Release notes, https://github.com/intgr/dogslow-sentry/blob/main/README.rst#changelog
Keywords: django debug watchdog middleware traceback sentry
Classifier: Development Status :: 6 - Mature
Classifier: Framework :: Django
Classifier: Framework :: Django :: 2.2
Classifier: Framework :: Django :: 3.0
Classifier: Framework :: Django :: 3.2
Classifier: Framework :: Django :: 3.2
Classifier: Framework :: Django :: 4.0
Classifier: Framework :: Django :: 4.1
Classifier: Framework :: Django :: 4.2
Classifier: Framework :: Django :: 5.0
Classifier: Intended Audience :: Developers
Classifier: License :: OSI Approved :: GNU Library or Lesser General Public License (LGPL)
Classifier: Natural Language :: English
Classifier: Operating System :: OS Independent
Classifier: Programming Language :: Python :: 3.7
Classifier: Programming Language :: Python :: 3.8
Classifier: Programming Language :: Python :: 3.9
Classifier: Programming Language :: Python :: 3.10
Classifier: Programming Language :: Python :: 3.11
Classifier: Programming Language :: Python :: 3.12
Classifier: Topic :: Software Development :: Debuggers
Classifier: Topic :: Utilities
Requires-Python: >=3.7
License-File: COPYING.txt
Requires-Dist: django >=2.2
Requires-Dist: sentry-sdk >=1.0
